{
	"name": "Ds_AzureSQLServer",
	"properties": {
		"linkedServiceName": {
			"referenceName": "LinkedService_AzureSQLServer",
			"type": "LinkedServiceReference"
		},
		"annotations": [],
		"type": "AzureSqlTable",
		"schema": [
			{
				"name": "id",
				"type": "int",
				"precision": 10
			},
			{
				"name": "name",
				"type": "varchar"
			},
			{
				"name": "location",
				"type": "varchar"
			},
			{
				"name": "pincode",
				"type": "int",
				"precision": 10
			},
			{
				"name": "cc",
				"type": "varchar"
			},
			{
				"name": "salary",
				"type": "int",
				"precision": 10
			}
		],
		"typeProperties": {
			"schema": "dbo",
			"table": "bankdata"
		}
	},
	"type": "Microsoft.DataFactory/factories/datasets"
}